arxiv_extractor/__init__.py
arxiv_extractor/cleanup.py
arxiv_extractor/extractor.py
arxiv_extractor/main.py
arxiv_extractor/pipeline.py
arxiv_extractor/scraper.py
arxiv_appendix_extractor-0.1.0.dist-info/METADATA
arxiv_appendix_extractor-0.1.0.dist-info/WHEEL
arxiv_appendix_extractor-0.1.0.dist-info/entry_points.txt
arxiv_appendix_extractor-0.1.0.dist-info/top_level.txt
arxiv_appendix_extractor-0.1.0.dist-info/RECORD
