Metadata-Version: 2.4
Name: arxiv-appendix-extractor
Version: 0.1.0
Summary: A tool to download arXiv papers, intelligently extract appendices with math formulas, and manage source files.
Author-email: Your Name <you@example.com>
License: MIT
Project-URL: Homepage, https://github.com/your-username/arxiv-appendix-extractor
Classifier: Programming Language :: Python :: 3
Classifier: License :: OSI Approved :: MIT License
Classifier: Operating System :: OS Independent
Classifier: Topic :: Scientific/Engineering
Classifier: Topic :: Text Processing
Requires-Python: >=3.8
Requires-Dist: requests
Requires-Dist: beautifulsoup4
Requires-Dist: lxml
Requires-Dist: feedparser
